merged/__init__.py
merged/__main__.py
merged/config.py
merged/version.py
merged/cli/__init__.py
merged/cli/main.py
merged/environment_configuration/__init__.py
merged/environment_configuration/view.py
merged/pull_requests/__init__.py
merged/pull_requests/resolver.py
merged/pull_requests/view.py
scripts/__init__.py
tests/__init__.py
tests/conftest.py
tests/test_pass.py
merged-0.1.0.dist-info/LICENSE.md
merged-0.1.0.dist-info/METADATA
merged-0.1.0.dist-info/WHEEL
merged-0.1.0.dist-info/entry_points.txt
merged-0.1.0.dist-info/top_level.txt
merged-0.1.0.dist-info/RECORD
