Metadata-Version: 2.1
Name: merged
Version: 0.1.0
Summary: A terminal UI dashboard to view python dependencies across Github repositories.
Download-URL: https://pypi.org/project/merged/
Author: Kyle Harrison
Author-email: kyle.harrison.dev@gmail.com
License: MIT
Project-URL: Funding, https://ko-fi.com/apoclyps
Project-URL: Say Thanks!, https://twitter.com/apoclyps
Project-URL: Source, https://github.com/apoclyps/merged
Project-URL: Tracker, https://github.com/apoclyps/merged/issues
Keywords: Merged
Classifier: Development Status :: 3 - Alpha
Classifier: Environment :: Console
Classifier: Intended Audience :: Developers
Classifier: License :: OSI Approved :: MIT License
Classifier: Natural Language :: English
Classifier: Operating System :: MacOS
Classifier: Operating System :: Microsoft :: Windows :: Windows 10
Classifier: Operating System :: Unix
Classifier: Programming Language :: Python :: 3.10
Classifier: Programming Language :: Python :: 3.11
Classifier: Topic :: Terminals
License-File: LICENSE.md
Requires-Dist: click (==8.1.3)
Requires-Dist: humanize (==4.6.0)
Requires-Dist: idna (==3.4)
Requires-Dist: keyboard (==0.13.5)
Requires-Dist: PyGithub (==1.58.1)
Requires-Dist: python-decouple (==3.7)
Requires-Dist: retrying (==1.3.4)
Requires-Dist: rich (==13.3.1)
